odoo/addons/quality_control_oca_timesheet/README.rst
odoo/addons/quality_control_oca_timesheet/__init__.py
odoo/addons/quality_control_oca_timesheet/__manifest__.py
odoo/addons/quality_control_oca_timesheet/i18n/ca.po
odoo/addons/quality_control_oca_timesheet/i18n/es.po
odoo/addons/quality_control_oca_timesheet/i18n/it.po
odoo/addons/quality_control_oca_timesheet/i18n/quality_control_oca_timesheet.pot
odoo/addons/quality_control_oca_timesheet/models/__init__.py
odoo/addons/quality_control_oca_timesheet/models/hr_timesheet.py
odoo/addons/quality_control_oca_timesheet/models/qc_inspection.py
odoo/addons/quality_control_oca_timesheet/readme/CONTRIBUTORS.md
odoo/addons/quality_control_oca_timesheet/readme/DESCRIPTION.md
odoo/addons/quality_control_oca_timesheet/readme/USAGE.md
odoo/addons/quality_control_oca_timesheet/static/description/icon.png
odoo/addons/quality_control_oca_timesheet/static/description/icon.svg
odoo/addons/quality_control_oca_timesheet/static/description/index.html
odoo/addons/quality_control_oca_timesheet/tests/__init__.py
odoo/addons/quality_control_oca_timesheet/tests/test_quality_control_oca_timesheet.py
odoo/addons/quality_control_oca_timesheet/views/qc_inspection_view.xml
odoo_addon_quality_control_oca_timesheet-17.0.1.0.0.4.dist-info/METADATA
odoo_addon_quality_control_oca_timesheet-17.0.1.0.0.4.dist-info/WHEEL
odoo_addon_quality_control_oca_timesheet-17.0.1.0.0.4.dist-info/top_level.txt
odoo_addon_quality_control_oca_timesheet-17.0.1.0.0.4.dist-info/RECORD
